correlated_ts_ci.py
correlated_ts_ci-0.2.0.dist-info/LICENSE
correlated_ts_ci-0.2.0.dist-info/WHEEL
correlated_ts_ci-0.2.0.dist-info/METADATA
correlated_ts_ci-0.2.0.dist-info/RECORD
