Metadata-Version: 2.1
Name: correlated-ts-ci
Version: 0.2.0
Summary: Estimate confidence intervals in means of correlated time series with a small number of effective samples (like molecular dynamics simulations). If your time series is long enough that the standard error levels off completely as a function of block length, then this method is overkill and simply using a block bootstrap sampling with a sufficiently large block length is probably sufficient.
License: GPL-3.0-or-later
Author: Brian Novak
Author-email: bnovak1@users.noreply.github.com
Requires-Python: >=3.9,<4.0
Classifier: License :: OSI Approved :: GNU General Public License v3 or later (GPLv3+)
Classifier: Programming Language :: Python :: 3
Classifier: Programming Language :: Python :: 3.10
Classifier: Programming Language :: Python :: 3.9
Requires-Dist: arch (>=4.16.1,<5.0.0)
Requires-Dist: joblib (>=0.17.0)
Requires-Dist: lmfit (>=1.0.2,<2.0.0)
Requires-Dist: numpy (>=1.2,<2.0)
